cloudops/__init__.py
cloudops/secret_manager/__init__.py
cloudops/secret_manager/json_secret.py
cloudops/secret_manager/protocol.py
cloudops/secret_manager/yaml_secret.py
cloudops_secret_manager-0.1.2.dist-info/LICENSE
cloudops_secret_manager-0.1.2.dist-info/WHEEL
cloudops_secret_manager-0.1.2.dist-info/METADATA
cloudops_secret_manager-0.1.2.dist-info/RECORD
